realtwin/__init__.py
realtwin/_realtwin.py
realtwin/data_lib/__init__.py
realtwin/data_lib/chattanooga.zip
realtwin/data_lib/data_lib_config.py
realtwin/data_lib/realtwin_config.yaml
realtwin/func_lib/__init__.py
realtwin/func_lib/_a_install_simulator/__init__.py
realtwin/func_lib/_a_install_simulator/check_sim_env.py
realtwin/func_lib/_a_install_simulator/inst_aimsun.py
realtwin/func_lib/_a_install_simulator/inst_sumo.py
realtwin/func_lib/_a_install_simulator/inst_vissim.py
realtwin/func_lib/_b_load_inputs/__init__.py
realtwin/func_lib/_b_load_inputs/loader_config.py
realtwin/func_lib/_c_abstract_scenario/__init__.py
realtwin/func_lib/_c_abstract_scenario/_abstractScenario.py
realtwin/func_lib/_c_abstract_scenario/_application.py
realtwin/func_lib/_c_abstract_scenario/_control.py
realtwin/func_lib/_c_abstract_scenario/_network.py
realtwin/func_lib/_c_abstract_scenario/_traffic.py
realtwin/func_lib/_c_abstract_scenario/rt_demand_generation.py
realtwin/func_lib/_c_abstract_scenario/rt_matchup_table_generation.py
realtwin/func_lib/_d_concrete_scenario/__init__.py
realtwin/func_lib/_d_concrete_scenario/_behavior.py
realtwin/func_lib/_d_concrete_scenario/_concreteScenario.py
realtwin/func_lib/_d_concrete_scenario/_demand.py
realtwin/func_lib/_d_concrete_scenario/_route.py
realtwin/func_lib/_d_concrete_scenario/_supply.py
realtwin/func_lib/_d_concrete_scenario/_trafficControl.py
realtwin/func_lib/_e_simulation/__init__.py
realtwin/func_lib/_e_simulation/_aimsun.py
realtwin/func_lib/_e_simulation/_generate_simulation.py
realtwin/func_lib/_e_simulation/_sumo.py
realtwin/func_lib/_e_simulation/_vissim.py
realtwin/func_lib/_f_calibration/__init__.py
realtwin/func_lib/_f_calibration/calibration_aimsun.py
realtwin/func_lib/_f_calibration/calibration_sumo.py
realtwin/func_lib/_f_calibration/calibration_vissim.py
realtwin/func_lib/_f_calibration/algo_aimsun/__init__.py
realtwin/func_lib/_f_calibration/algo_sumo/__init__.py
realtwin-0.1.0.dist-info/licenses/LICENSE
realtwin-0.1.0.dist-info/METADATA
realtwin-0.1.0.dist-info/WHEEL
realtwin-0.1.0.dist-info/top_level.txt
realtwin-0.1.0.dist-info/RECORD
