Metadata-Version: 2.4
Name: realtwin
Version: 0.1.0
Summary: A Unified Simulation Scenario Generation Tool for Mobility Research
Author-email: ORNL-RealTwin <realtwin@ornl.gov>
Maintainer-email: ORNL-RealTwin <realtwin@ornl.gov>
Project-URL: Homepage, https://github.com/ORNL-Real-Sim/Real-Twin
Project-URL: Documentation, https://real-twin.readthedocs.io/en/latest/
Project-URL: Bug Tracker, https://github.com/ORNL-Real-Sim/Real-Twin/issues
Project-URL: Contact, https://github.com/ORNL-Real-Sim/Real-Twin
Keywords: Real-Twin,Digital Twin,Traffic Micro-simulation,Scenario Generation,Connected and Automated Vehicles,CAV,Traffic Simulation,SUMO,VISSIM,AIMSUN
Classifier: Programming Language :: Python :: 3
Classifier: Programming Language :: Python :: 3.10
Classifier: Programming Language :: Python :: 3.11
Classifier: Programming Language :: Python :: 3.12
Classifier: Programming Language :: Python :: 3.13
Classifier: Intended Audience :: Developers
Classifier: Operating System :: OS Independent
Classifier: Topic :: Software Development :: Libraries
Requires-Python: >=3.10
License-File: LICENSE
Requires-Dist: pandas
Requires-Dist: networkx
Requires-Dist: openpyxl
Requires-Dist: osmnx
Requires-Dist: sumolib
Requires-Dist: traci
Requires-Dist: pyproj
Requires-Dist: pyufunc>=0.4.1
Requires-Dist: PyYAML
Requires-Dist: Requests
Requires-Dist: Shapely
Requires-Dist: mealpy
Requires-Dist: xlrd
Requires-Dist: folium
Requires-Dist: matplotlib
Requires-Dist: rich
Dynamic: license-file
